LICENSE
MANIFEST.in
README.rst
setup.py
vinli_tornado_auth/__init__.py
vinli_tornado_auth/auth.py
vinli_tornado_auth.egg-info/PKG-INFO
vinli_tornado_auth.egg-info/SOURCES.txt
vinli_tornado_auth.egg-info/dependency_links.txt
vinli_tornado_auth.egg-info/top_level.txt