Metadata-Version: 1.1
Name: vinli-tornado-auth
Version: 0.1.0
Summary: Tornado web authentication for the Vinli Platform.
Home-page: https://github.com/gaker/vinli-tornado-auth
Author: Greg Aker
Author-email: greg@gregaker.net
License: UNKNOWN
Download-URL: https://github.com/gaker/vinli-tornado-auth/archive/0.1.0.tar.gz
Platform: UNKNOWN
Classifier: License :: OSI Approved :: MIT License
Classifier: Environment :: Web Environment
Classifier: Programming Language :: Python :: 2
Classifier: Programming Language :: Python :: 2.7
Classifier: Programming Language :: Python :: 3
Classifier: Programming Language :: Python :: 3.3
Classifier: Programming Language :: Python :: 3.4
Classifier: Programming Language :: Python :: Implementation :: CPython
Classifier: Programming Language :: Python :: Implementation :: PyPy
